packages/evo-blockmodels/LICENSE.md
packages/evo-blockmodels/README.md
packages/evo-blockmodels/pyproject.toml
packages/evo-blockmodels/docs/examples/quickstart.ipynb
packages/evo-blockmodels/src/evo/blockmodels/__init__.py
packages/evo-blockmodels/src/evo/blockmodels/_model_config.py
packages/evo-blockmodels/src/evo/blockmodels/_types.py
packages/evo-blockmodels/src/evo/blockmodels/_utils.py
packages/evo-blockmodels/src/evo/blockmodels/client.py
packages/evo-blockmodels/src/evo/blockmodels/data.py
packages/evo-blockmodels/src/evo/blockmodels/exceptions.py
packages/evo-blockmodels/src/evo/blockmodels/io.py
packages/evo-blockmodels/src/evo/blockmodels/endpoints/__init__.py
packages/evo-blockmodels/src/evo/blockmodels/endpoints/models.py
packages/evo-blockmodels/src/evo/blockmodels/endpoints/api/__init__.py
packages/evo-blockmodels/src/evo/blockmodels/endpoints/api/column_operations_api.py
packages/evo-blockmodels/src/evo/blockmodels/endpoints/api/jobs_api.py
packages/evo-blockmodels/src/evo/blockmodels/endpoints/api/metadata_api.py
packages/evo-blockmodels/src/evo/blockmodels/endpoints/api/operations_api.py
packages/evo-blockmodels/src/evo/blockmodels/endpoints/api/reports_api.py
packages/evo-blockmodels/src/evo/blockmodels/endpoints/api/units_api.py
packages/evo-blockmodels/src/evo/blockmodels/endpoints/api/versions_api.py
packages/evo-blockmodels/tests/test_block_model_service_client.py
packages/evo-blockmodels/tests/test_bm_size_options_conversion.py
packages/evo-blockmodels/tests/test_create.py
packages/evo-blockmodels/tests/test_list_block_models.py
packages/evo-blockmodels/tests/test_update.py
packages/evo-blockmodels/tests/utils.py
packages/evo-colormaps/LICENSE.md
packages/evo-colormaps/README.md
packages/evo-colormaps/pyproject.toml
packages/evo-colormaps/docs/examples/quickstart.ipynb
packages/evo-colormaps/src/evo/colormaps/__init__.py
packages/evo-colormaps/src/evo/colormaps/_model_config.py
packages/evo-colormaps/src/evo/colormaps/client.py
evo_sdk-0.1.18.dist-info/METADATA
evo_sdk-0.1.18.dist-info/WHEEL
evo_sdk-0.1.18.dist-info/licenses/LICENSE.md
evo_sdk-0.1.18.dist-info/RECORD
