Metadata-Version: 2.4
Name: evo-sdk
Version: 0.1.18
Summary: Python SDK for using Seequent Evo
Project-URL: Source, https://github.com/SeequentEvo/evo-python-sdk
Project-URL: Tracker, https://github.com/SeequentEvo/evo-python-sdk/issues
Project-URL: Homepage, https://www.seequent.com/
Project-URL: Documentation, https://developer.seequent.com/
License-File: LICENSE.md
Requires-Python: >=3.10
Requires-Dist: evo-blockmodels[aiohttp,notebooks,pyarrow]>=0.1.0
Requires-Dist: evo-colormaps[aiohttp,notebooks]>=0.0.2
Requires-Dist: evo-compute[aiohttp,notebooks]>=0.0.1rc2
Requires-Dist: evo-files[aiohttp,notebooks]>=0.2.3
Requires-Dist: evo-objects[aiohttp,notebooks,utils]>=0.3.3
Requires-Dist: evo-sdk-common[aiohttp,jmespath,notebooks]>=0.5.12
Requires-Dist: jupyter
